sogou_tr/__init__.py
sogou_tr/sogou_tr.py
sogou_tr-0.1.1.dist-info/WHEEL
sogou_tr-0.1.1.dist-info/METADATA
sogou_tr-0.1.1.dist-info/RECORD
