Metadata-Version: 2.1
Name: sogou-tr
Version: 0.1.1
Summary: sogou translate no frills
Home-page: https://github.com/ffreemt/sogou-tr-simple
License: MIT
Author: freemt
Requires-Python: >=3.7,<4.0
Classifier: License :: OSI Approved :: MIT License
Classifier: Programming Language :: Python :: 3
Classifier: Programming Language :: Python :: 3.7
Classifier: Programming Language :: Python :: 3.8
Classifier: Programming Language :: Python :: 3.9
Requires-Dist: fuzzywuzzy (>=0.18.0,<0.19.0)
Requires-Dist: httpx (>=0.17.1,<0.18.0)
Requires-Dist: langid (>=1.1.6,<2.0.0)
Requires-Dist: logzero (>=1.7.0,<2.0.0)
Project-URL: Repository, https://github.com/ffreemt/sogou-tr-simple
